local_stdio/__init__.py
local_stdio-0.1.0.dist-info/WHEEL
local_stdio-0.1.0.dist-info/entry_points.txt
local_stdio-0.1.0.dist-info/METADATA
local_stdio-0.1.0.dist-info/RECORD
