Metadata-Version: 2.3
Name: local-stdio
Version: 0.1.0
Summary: Add your description here
Author: zhangxiaoyao
Author-email: zhangxiaoyao <zhangxiaoyao@wxdata.cn>
Requires-Dist: mcp[cli]>=1.20.0
Requires-Python: >=3.13
